mantarix_desktop/__init__.py
mantarix_desktop/version.py
mantarix_desktop-1.0.0.dist-info/METADATA
mantarix_desktop-1.0.0.dist-info/WHEEL
mantarix_desktop-1.0.0.dist-info/RECORD
