Metadata-Version: 2.3
Name: mantarix-desktop
Version: 1.0.0
Summary: Mantarix Desktop client in Flutter
License: Apache-2.0
Author: Mantarix Systems Inc.
Author-email: hello@mantarix.dev
Requires-Python: >=3.8,<4.0
Classifier: License :: OSI Approved :: Apache Software License
Classifier: Programming Language :: Python :: 3
Classifier: Programming Language :: Python :: 3.8
Classifier: Programming Language :: Python :: 3.9
Classifier: Programming Language :: Python :: 3.10
Classifier: Programming Language :: Python :: 3.11
Classifier: Programming Language :: Python :: 3.12
Classifier: Programming Language :: Python :: 3.13
Requires-Dist: mantarix (==1.0.0)
Project-URL: repository, https://github.com/mantarix-dev/mantarix
